traccar_api/__init__.py
traccar_api/api.py
traccar_api/traccar_errors/__init__.py
traccar_api/traccar_errors/traccar_api_errors.py
traccar_api-0.3.0.dist-info/METADATA
traccar_api-0.3.0.dist-info/WHEEL
traccar_api-0.3.0.dist-info/top_level.txt
traccar_api-0.3.0.dist-info/RECORD
