Metadata-Version: 2.1
Name: traccar_api
Version: 0.3.0
Summary: Python client for interacting with Traccar GPS tracking API
Home-page: https://github.com/LiGuru/traccar_api
Author: LiGuru
Author-email: services.nvlahovski@gmail.com
Classifier: Programming Language :: Python :: 3
Classifier: License :: OSI Approved :: MIT License
Classifier: Operating System :: OS Independent
Requires-Python: >=3.9
Requires-Dist: requests >=2.25.1
